pm_sdk/__init__.py
pm_sdk/core.py
pm_sdk-0.1.13.dist-info/METADATA
pm_sdk-0.1.13.dist-info/WHEEL
pm_sdk-0.1.13.dist-info/top_level.txt
pm_sdk-0.1.13.dist-info/RECORD
