Metadata-Version: 2.4
Name: pm_sdk
Version: 0.1.13
Summary: SDK for interacting with Photometrica
Author: Westboro Photonics
Requires-Dist: requests>=2.32.1
Dynamic: author
Dynamic: description
Dynamic: description-content-type
Dynamic: requires-dist
Dynamic: summary
